detabase/__init__.py
detabase/base_models.py
detabase/casting.py
detabase/config.py
detabase/constants.py
detabase/context.py
detabase/descriptor.py
detabase/deta_model.py
detabase/engine.py
detabase/enums.py
detabase/form.py
detabase/json_encoder.py
detabase/model_key.py
detabase/protocols.py
detabase/regex.py
detabase/types.py
detabase-0.2.6.dist-info/WHEEL
detabase-0.2.6.dist-info/METADATA
detabase-0.2.6.dist-info/RECORD
